LICENSE.md
README.md
pyproject.toml
setup.cfg
setup.py
src/esrf_ontology/__init__.py
src/esrf_ontology.egg-info/PKG-INFO
src/esrf_ontology.egg-info/SOURCES.txt
src/esrf_ontology.egg-info/dependency_links.txt
src/esrf_ontology.egg-info/requires.txt
src/esrf_ontology.egg-info/top_level.txt
src/esrf_ontology/ontology/PaNET.owl
src/esrf_ontology/ontology/__init__.py
src/esrf_ontology/technique/__init__.py
src/esrf_ontology/technique/panet.py
src/esrf_ontology/technique/types.py
src/esrf_ontology/tests/__init__.py
src/esrf_ontology/tests/test_multi_technique_metadata.py
src/esrf_ontology/tests/test_single_technique_metadata.py
src/esrf_ontology/tests/test_techniques.py