Metadata-Version: 2.1
Name: esrf-ontology
Version: 0.1.0b0
Summary: ESRF Ontology
Home-page: https://gitlab.esrf.fr/dau/ontology/esrf-ontology/
Author: ESRF
Author-email: wout.de_nolf@esrf.fr
License: MIT
Project-URL: Source, https://gitlab.esrf.fr/dau/ontology/esrf-ontology/
Project-URL: Documentation, https://esrf-ontology.readthedocs.io/
Project-URL: Tracker, https://gitlab.esrf.fr/dau/ontology/esrf-ontology/issues/
Classifier: Intended Audience :: Science/Research
Classifier: License :: OSI Approved :: MIT License
Classifier: Programming Language :: Python :: 3
Requires-Python: >=3.6
License-File: LICENSE.md
Requires-Dist: owlready2
Requires-Dist: importlib_resources; python_version < "3.9"
Provides-Extra: test
Requires-Dist: pytest>=7; extra == "test"
Provides-Extra: dev
Requires-Dist: pytest>=7; extra == "dev"
Requires-Dist: black>=22; extra == "dev"
Requires-Dist: flake8>=4; extra == "dev"
Provides-Extra: doc
Requires-Dist: pytest>=7; extra == "doc"
Requires-Dist: sphinx>=4.5; extra == "doc"
Requires-Dist: sphinx-autodoc-typehints>=1.16; extra == "doc"
Requires-Dist: pydata-sphinx-theme<0.15; extra == "doc"
Requires-Dist: tabulate; extra == "doc"
